bn_adjustable_bed/__init__.py
bn_adjustable_bed/app_api/__init__.py
bn_adjustable_bed/app_api/__main__.py
bn_adjustable_bed/app_api/api.py
bn_adjustable_bed/app_api/config.py
bn_adjustable_bed/app_api/datastore.py
bn_adjustable_bed/bed_socket/__init__.py
bn_adjustable_bed/bed_socket/__main__.py
bn_adjustable_bed/bed_socket/bedsocket.py
bn_adjustable_bed/bed_socket/config.py
bn_adjustable_bed/bed_socket/datastore.py
bn_adjustable_bed/bed_socket/loghandler.py
bn_adjustable_bed/bed_socket/process_commands.py
bn_adjustable_bed/config/app_api.yml
bn_adjustable_bed/config/bed_socket.yml
bn_adjustable_bed/config/controller_api.yml
bn_adjustable_bed/controller_api/__init__.py
bn_adjustable_bed/controller_api/__main__.py
bn_adjustable_bed/controller_api/api.py
bn_adjustable_bed/controller_api/config.py
bn_adjustable_bed/controller_api/datastore.py
bn_adjustable_bed-1.3.14.dist-info/entry_points.txt
bn_adjustable_bed-1.3.14.dist-info/LICENSE
bn_adjustable_bed-1.3.14.dist-info/WHEEL
bn_adjustable_bed-1.3.14.dist-info/METADATA
bn_adjustable_bed-1.3.14.dist-info/RECORD
