Metadata-Version: 2.1
Name: bn-adjustable-bed
Version: 1.3.14
Summary: BN Adjustable Bed Mock API and Socket Interface
Home-page: https://github.com/trevorlauder/bn-adjustable-bed
License: MIT
Author: Trevor Lauder
Author-email: trevor@lauder.family
Maintainer: Trevor Lauder
Maintainer-email: trevor@lauder.family
Requires-Python: >=3.10,<4.0
Classifier: License :: OSI Approved :: MIT License
Classifier: Programming Language :: Python :: 3
Classifier: Programming Language :: Python :: 3.10
Classifier: Topic :: Home Automation
Provides-Extra: test
Requires-Dist: fastapi (>=0.70,<0.86)
Requires-Dist: pytest (>=6.2,<8.0); extra == "test"
Requires-Dist: pytest-cov (>=3,<5); extra == "test"
Requires-Dist: pytest-mock (>=3.6,<4.0); extra == "test"
Requires-Dist: pyyaml (>=6.0,<7.0)
Requires-Dist: redis (>=4.0,<5.0)
Requires-Dist: requests (>=2.26,<3.0); extra == "test"
Requires-Dist: uvicorn (>=0.15,<0.19)
Project-URL: Repository, https://github.com/trevorlauder/bn-adjustable-bed
